yaqd_zaber/VERSION
yaqd_zaber/__init__.py
yaqd_zaber/__version__.py
yaqd_zaber/_serial.py
yaqd_zaber/_zaber_binary.py
yaqd_zaber/zaber-binary.avpr
yaqd_zaber/zaber-binary.toml
yaqd_zaber-2022.11.0.dist-info/entry_points.txt
yaqd_zaber-2022.11.0.dist-info/LICENSE
yaqd_zaber-2022.11.0.dist-info/WHEEL
yaqd_zaber-2022.11.0.dist-info/METADATA
yaqd_zaber-2022.11.0.dist-info/RECORD
