Metadata-Version: 2.1
Name: yaqd-zaber
Version: 2022.11.0
Summary: yaq daemons for hardware from Zaber Technologies
Home-page: https://yaq.fyi
Author: yaq Developers
Author-email: git@ksunden.space
Requires-Python: >=3.7
Classifier: Development Status :: 4 - Beta
Classifier: Intended Audience :: Science/Research
Classifier: License :: OSI Approved :: GNU Lesser General Public License v3 (LGPLv3)
Classifier: Natural Language :: English
Classifier: Programming Language :: Python :: 3
Classifier: Programming Language :: Python :: 3.7
Classifier: Programming Language :: Python :: 3.8
Classifier: Topic :: Scientific/Engineering
Requires-Dist: yaqd-core>=2020.06.3
Requires-Dist: zaber.serial
Requires-Dist: black ; extra == "dev"
Requires-Dist: pre-commit ; extra == "dev"
Project-URL: Issues, https://gitlab.com/yaq/yaqd-zaber/issues
Project-URL: Source, https://gitlab.com/yaq/yaqd-zaber
Provides-Extra: dev
